{
    "head_word": "דְּדָן",
    "pos": "nom propre [d'un lieu & d'un peuple]",
    "primary": null,
    "description": "sous la figure de fils de רַעֲמָה et petit-fils de כּוּשׁ",
    "senses": [
        {
            "number": 1,
            "primary": null,
            "description": "sous la figure de fils de רַעֲמָה et petit-fils de כּוּשׁ"
        },
        {
            "number": 2,
            "primary": null,
            "description": "comme fils de יָקְשָׁן père de אַשּׁוּרִם"
        }
    ]
}
