{
    "head_word": "מִחְיָה",
    "pos": "nom féminin",
    "primary": "conservation de la vie, subsistance",
    "description": null,
    "senses": [
        {
            "number": 1,
            "primary": null,
            "description": null
        },
        {
            "number": 2,
            "primary": null,
            "description": null
        },
        {
            "number": 3,
            "primary": null,
            "description": null
        },
        {
            "number": 4,
            "primary": null,
            "description": null
        }
    ]
}
