{
    "head_word": "הִלּוּל",
    "pos": "nom [masculin]",
    "primary": "réjouissance, louange",
    "description": "c.-à-d. une réjouissance de vendange, festivité, liée à l'action de grâces",
    "senses": [
        {
            "number": 1,
            "primary": null,
            "description": "c.-à-d. une réjouissance de vendange, festivité, liée à l'action de grâces"
        },
        {
            "number": 2,
            "primary": null,
            "description": "de louange à ׳י"
        }
    ]
}
