{
    "head_word": "כִּלָּיוֺן",
    "pos": "nom masculin",
    "primary": "défaillance, langueur",
    "description": null,
    "senses": [
        {
            "number": 1,
            "primary": "défaillance, langueur",
            "description": null
        },
        {
            "number": 2,
            "primary": "anéantissement",
            "description": null
        },
        {
            "number": 3,
            "primary": null,
            "description": null
        },
        {
            "number": 4,
            "primary": null,
            "description": null
        }
    ]
}
