{
    "head_word": "חָזָה",
    "pos": "verbe",
    "primary": "voir, contempler",
    "description": "(presque entierement en poesie)",
    "senses": [
        {
            "number": 1,
            "primary": null,
            "description": null
        },
        {
            "number": 2,
            "primary": null,
            "description": "voir en tant que voyant dans l'etat extatique, avec accusatif de la vision vue"
        },
        {
            "number": 3,
            "primary": null,
            "description": null
        }
    ]
}
