{
    "head_word": "נֶ֫דֶר",
    "pos": "nom masculin",
    "primary": "voeu",
    "description": "de service personnel a ׳י",
    "senses": [
        {
            "number": 1,
            "primary": null,
            "description": "de service personnel a ׳י"
        },
        {
            "number": 2,
            "primary": null,
            "description": "en general de toute sorte d'offrandes votives ou de dons promis a ׳י"
        },
        {
            "number": 3,
            "primary": null,
            "description": "la fille de Jephte comme עולה"
        },
        {
            "number": 4,
            "primary": null,
            "description": "l'interdit"
        },
        {
            "number": 5,
            "primary": null,
            "description": "|| עוֺלָה"
        },
        {
            "number": 6,
            "primary": null,
            "description": "une fois de l'idolatrie"
        }
    ]
}
