{
    "head_word": "מַתַּנְיָ֫הוּ",
    "pos": "nom propre, masculin",
    "primary": null,
    "description": "dernier roi de Juda, nom change en Sedecias",
    "senses": [
        {
            "number": 1,
            "primary": null,
            "description": "dernier roi de Juda, nom change en Sedecias"
        },
        {
            "number": 2,
            "primary": null,
            "description": "nom de Levite"
        },
        {
            "number": 3,
            "primary": null,
            "description": "nom de Levite"
        },
        {
            "number": 4,
            "primary": null,
            "description": "nom de plusieurs qui prirent des femmes etrangeres"
        }
    ]
}
