{
    "head_word": "סָתַר",
    "pos": "verbe",
    "primary": "cacher, dissimuler",
    "description": "(c.-a-d. abriter)",
    "senses": [
        {
            "number": 1,
            "primary": null,
            "description": null
        },
        {
            "number": 2,
            "primary": null,
            "description": null
        },
        {
            "number": 3,
            "primary": null,
            "description": "une personne"
        },
        {
            "number": 4,
            "primary": null,
            "description": "surtout cacher la face"
        }
    ]
}
