{
    "head_word": "כַּ֫חַשׁ",
    "pos": "nom masculin",
    "primary": "mensonge",
    "description": "of Job's affliction",
    "senses": [
        {
            "number": 1,
            "primary": "mensonge",
            "description": null
        },
        {
            "number": 2,
            "primary": "maigreur",
            "description": null
        },
        {
            "number": 3,
            "primary": null,
            "description": null
        },
        {
            "number": 4,
            "primary": null,
            "description": "of Job's affliction"
        }
    ]
}
